Metadata-Version: 2.1
Name: odoo-addon-mass-mailing-custom-unsubscribe-event
Version: 15.0.1.0.0.3
Summary: Allow to unsubscribe discretely from an event
Home-page: https://github.com/OCA/social
Author: Tecnativa, Odoo Community Association (OCA)
Author-email: support@odoo-community.org
License: AGPL-3
Platform: UNKNOWN
Classifier: Programming Language :: Python
Classifier: Framework :: Odoo
Classifier: Framework :: Odoo :: 15.0
Classifier: License :: OSI Approved :: GNU Affero General Public License v3
Requires-Python: >=3.8
Requires-Dist: odoo-addon-mass-mailing-custom-unsubscribe <15.1dev,>=15.0dev
Requires-Dist: odoo <15.1dev,>=15.0a
